fcmaker/__init__.py
fcmaker/__main__.py
fcmaker/fcmaker.py
fcmaker/fcmaker_espresso.py
fcmaker/fcmaker_hawki.py
fcmaker/fcmaker_instrument_dispatch.py
fcmaker/fcmaker_metadata.py
fcmaker/fcmaker_muse.py
fcmaker/fcmaker_plots.py
fcmaker/fcmaker_tools.py
fcmaker/fcmaker_version.py
fcmaker/fcmaker_xshooter.py
fcmaker/p2api.py
fcmaker/docs/.buildinfo
fcmaker/docs/acknowledge.html
fcmaker/docs/changelog.html
fcmaker/docs/faq.html
fcmaker/docs/genindex.html
fcmaker/docs/index.html
fcmaker/docs/installation.html
fcmaker/docs/objects.inv
fcmaker/docs/py-modindex.html
fcmaker/docs/running.html
fcmaker/docs/search.html
fcmaker/docs/searchindex.js
fcmaker/docs/.doctrees/acknowledge.doctree
fcmaker/docs/.doctrees/changelog.doctree
fcmaker/docs/.doctrees/environment.pickle
fcmaker/docs/.doctrees/faq.doctree
fcmaker/docs/.doctrees/index.doctree
fcmaker/docs/.doctrees/installation.doctree
fcmaker/docs/.doctrees/running.doctree
fcmaker/docs/.doctrees/modules/fcmaker.doctree
fcmaker/docs/.doctrees/modules/modules.doctree
fcmaker/docs/_images/WFM_AO_DSS2-Red.png
fcmaker/docs/_sources/acknowledge.rst.txt
fcmaker/docs/_sources/changelog.rst.txt
fcmaker/docs/_sources/faq.rst.txt
fcmaker/docs/_sources/index.rst.txt
fcmaker/docs/_sources/installation.rst.txt
fcmaker/docs/_sources/running.rst.txt
fcmaker/docs/_sources/modules/fcmaker.rst.txt
fcmaker/docs/_sources/modules/modules.rst.txt
fcmaker/docs/_static/ajax-loader.gif
fcmaker/docs/_static/basic.css
fcmaker/docs/_static/comment-bright.png
fcmaker/docs/_static/comment-close.png
fcmaker/docs/_static/comment.png
fcmaker/docs/_static/doctools.js
fcmaker/docs/_static/down-pressed.png
fcmaker/docs/_static/down.png
fcmaker/docs/_static/file.png
fcmaker/docs/_static/jquery-3.1.0.js
fcmaker/docs/_static/jquery.js
fcmaker/docs/_static/minus.png
fcmaker/docs/_static/plus.png
fcmaker/docs/_static/pygments.css
fcmaker/docs/_static/searchtools.js
fcmaker/docs/_static/underscore-1.3.1.js
fcmaker/docs/_static/underscore.js
fcmaker-105.0.0.dist-info/LICENSE
fcmaker-105.0.0.dist-info/METADATA
fcmaker-105.0.0.dist-info/WHEEL
fcmaker-105.0.0.dist-info/entry_points.txt
fcmaker-105.0.0.dist-info/top_level.txt
fcmaker-105.0.0.dist-info/RECORD
